Anteater/__init__.py
Anteater/anteater.py
Anteater/main.py
anteater_sh-2.0.1.dist-info/LICENSE.txt
anteater_sh-2.0.1.dist-info/METADATA
anteater_sh-2.0.1.dist-info/WHEEL
anteater_sh-2.0.1.dist-info/top_level.txt
anteater_sh-2.0.1.dist-info/RECORD
