Metadata-Version: 2.1
Name: anteater-sh
Version: 2.0.1
Summary: A DNA sequence sensitive filter
Home-page: https://github.com/pypa/sampleproject
Author: WULI Hui
Author-email: adairmillersh@gmail.com
License: UNKNOWN
Project-URL: Bug Tracker, https://github.com/pypa/sampleproject/issues
Platform: UNKNOWN
Classifier: Programming Language :: Python :: 3
Classifier: License :: OSI Approved :: MIT License
Classifier: Operating System :: OS Independent
Requires-Python: >=3.6
